paramify/__init__.py
paramify/paramify.py
paramify/paramify_web.py
paramify/static/index.html
paramify/static/assets/index-C3Xrcbp_.js
paramify/static/assets/index-DwXyNpx-.css
tests/__init__.py
tests/test_paramify_callback.py
tests/test_paramify_cli.py
tests/test_paramify_dynamic.py
tests/test_paramify_init.py
tests/test_paramify_misc.py
tests/test_paramify_performance.py
tests/test_paramify_persist.py
tests/test_paramify_validation.py
paramify-0.1.4.dist-info/LICENSE
paramify-0.1.4.dist-info/METADATA
paramify-0.1.4.dist-info/WHEEL
paramify-0.1.4.dist-info/top_level.txt
paramify-0.1.4.dist-info/RECORD
