Metadata-Version: 2.2
Name: paramify
Version: 0.1.4
Summary: A lightweight Python library for dynamic parameter management and runtime configuration.
Home-page: https://github.com/luxai-qtrobot/paramify
Author: Ali PAikan
Author-email: ali.paikan@gmail.com
License: MIT
Project-URL: Documentation, https://github.com/luxai-qtrobot/paramify#readme
Project-URL: Source, https://github.com/luxai-qtrobot/paramify
Project-URL: Tracker, https://github.com/luxai-qtrobot/paramify/issues
Keywords: parameter management configuration dynamic runtime UI
Classifier: Development Status :: 4 - Beta
Classifier: Intended Audience :: Developers
Classifier: License :: OSI Approved :: MIT License
Classifier: Programming Language :: Python :: 3
Classifier: Programming Language :: Python :: 3.7
Classifier: Programming Language :: Python :: 3.8
Classifier: Programming Language :: Python :: 3.9
Classifier: Programming Language :: Python :: 3.10
Classifier: Topic :: Software Development :: Libraries
Classifier: Topic :: Software Development :: Libraries :: Application Frameworks
Requires-Python: >=3.7
License-File: LICENSE
Requires-Dist: Flask>=2.0.0
Requires-Dist: pydantic>=1.10.0
Requires-Dist: ruamel.yaml>=0.17.0
Dynamic: author
Dynamic: author-email
Dynamic: classifier
Dynamic: description
Dynamic: description-content-type
Dynamic: home-page
Dynamic: keywords
Dynamic: license
Dynamic: project-url
Dynamic: requires-dist
Dynamic: requires-python
Dynamic: summary
